{
  "image": "images/Одноэтажный комплекс Одуванчик.png",
  "zones": [
    {
      "id": 1,
      "name": "Зона 1",
      "polygons": [[[0.0446, 0.0787], [0.2285, 0.0787], [0.2285, 0.4595], [0.0446, 0.4595]]],
      "label": [0.1366, 0.2691]
    },
    {
      "id": 2,
      "name": "Зона 2",
      "polygons": [[[0.2285, 0.0787], [0.3218, 0.0787], [0.3218, 0.4595], [0.2285, 0.4595]]],
      "label": [0.2752, 0.2691]
    },
    {
      "id": 3,
      "name": "Зона 3",
      "polygons": [[[0.3218, 0.0787], [0.5071, 0.0787], [0.5071, 0.4595], [0.3218, 0.4595]]],
      "label": [0.3682, 0.2691]
    },
    {
      "id": 4,
      "name": "Зона 4",
      "polygons": [[[0.5071, 0.0787], [0.5997, 0.0787], [0.5997, 0.4595], [0.5071, 0.4595]]],
      "label": [0.5071, 0.2691]
    },
    {
      "id": 5,
      "name": "Зона 5",
      "polygons": [[[0.5997, 0.0787], [0.7863, 0.0787], [0.7863, 0.4595], [0.5997, 0.4595]]],
      "label": [0.6930, 0.2691]
    },
    {
      "id": 6,
      "name": "Зона 6",
      "polygons": [[[0.7863, 0.0787], [0.9682, 0.0787], [0.9682, 0.4595], [0.7863, 0.4595]]],
      "label": [0.8773, 0.2691]
    },
    {
      "id": 7,
      "name": "Зона 7",
      "polygons": [[[0.0446, 0.5861], [0.1400, 0.5861], [0.1400, 0.9567], [0.0446, 0.9567]]],
      "label": [0.0923, 0.7714]
    },
    {
      "id": 8,
      "name": "Зона 8",
      "polygons": [[[0.1400, 0.5861], [0.2285, 0.5861], [0.2285, 0.9567], [0.1400, 0.9567]]],
      "label": [0.1842, 0.7714]
    },
    {
      "id": 9,
      "name": "Зона 9",
      "polygons": [[[0.2285, 0.5861], [0.3218, 0.5861], [0.3218, 0.9567], [0.2285, 0.9567]]],
      "label": [0.2752, 0.7714]
    },
    {
      "id": 10,
      "name": "Зона 10",
      "polygons": [[[0.3218, 0.5861], [0.4145, 0.5861], [0.4145, 0.9567], [0.3218, 0.9567]]],
      "label": [0.3682, 0.7714]
    },
    {
      "id": 11,
      "name": "Зона 11",
      "polygons": [[[0.4145, 0.5861], [0.5071, 0.5861], [0.5071, 0.9567], [0.4145, 0.9567]]],
      "label": [0.4608, 0.7714]
    },
    {
      "id": 12,
      "name": "Зона 12",
      "polygons": [[[0.5071, 0.5861], [0.5997, 0.5861], [0.5997, 0.9567], [0.5071, 0.9567]]],
      "label": [0.5534, 0.7714]
    },
    {
      "id": 13,
      "name": "Зона 13",
      "polygons": [[[0.5997, 0.5861], [0.7863, 0.5861], [0.7863, 0.9567], [0.5997, 0.9567]]],
      "label": [0.6930, 0.7714]
    },
    {
      "id": 14,
      "name": "Зона 14",
      "polygons": [[[0.7863, 0.5861], [0.9682, 0.5861], [0.9682, 0.9567], [0.7863, 0.9567]]],
      "label": [0.8773, 0.7714]
    },
    {
      "id": 15,
      "name": "Зона 15",
      "polygons": [[[0.0446, 0.4595], [0.9682, 0.4595], [0.9682, 0.5861], [0.0446, 0.5861]]],
      "label": [0.5064, 0.5228]
    }
  ]
}
